pyaragorn-0.3.0.dist-info/RECORD
pyaragorn-0.3.0.dist-info/WHEEL
pyaragorn-0.3.0.dist-info/METADATA
pyaragorn-0.3.0.dist-info/licenses/COPYING
pyaragorn/lib.pyi
pyaragorn/CMakeLists.txt
pyaragorn/__init__.py
pyaragorn/lib.pyx
pyaragorn/py.typed
pyaragorn/lib.cpython-310-darwin.so
pyaragorn/tests/requirements.txt
pyaragorn/tests/__init__.py
pyaragorn/tests/test_rna_finder.py
pyaragorn/tests/test_doctest.py
pyaragorn/tests/fasta.py
pyaragorn/tests/data/CP001621.default.txt
pyaragorn/tests/data/__init__.py
pyaragorn/tests/data/CP001621.ps95.txt
pyaragorn/tests/data/CP001621.fna.gz
