Metadata-Version: 2.4
Name: pyaragorn
Version: 0.3.0
Summary: Cython bindings and Python interface to ARAGORN, a tRNA and mtRNA detection software.
Keywords: bioinformatics,gene,transfer,messenger,RNA
Author-Email: Martin Larralde <martin.larralde@embl.de>
License-Expression: GPL-3.0-or-later
Classifier: Development Status :: 3 - Alpha
Classifier: Intended Audience :: Developers
Classifier: Intended Audience :: Science/Research
Classifier: Operating System :: OS Independent
Classifier: Programming Language :: C
Classifier: Programming Language :: Cython
Classifier: Programming Language :: Python :: 3.7
Classifier: Programming Language :: Python :: 3.8
Classifier: Programming Language :: Python :: 3.9
Classifier: Programming Language :: Python :: 3.10
Classifier: Programming Language :: Python :: 3.11
Classifier: Programming Language :: Python :: 3.12
Classifier: Programming Language :: Python :: 3.13
Classifier: Programming Language :: Python :: 3.14
Classifier: Programming Language :: Python :: Implementation :: CPython
Classifier: Programming Language :: Python :: Implementation :: PyPy
Classifier: Topic :: Scientific/Engineering :: Bio-Informatics
Classifier: Topic :: Scientific/Engineering :: Medical Science Apps.
Classifier: Typing :: Typed
Project-URL: Documentation, https://pyaragorn.readthedocs.io/en/stable/
Project-URL: Bug Tracker, https://github.com/althonos/pyaragorn/issues
Project-URL: Changelog, https://github.com/althonos/pyaragorn/blob/master/CHANGELOG.md
Project-URL: Coverage, https://codecov.io/gh/althonos/pyaragorn/
Project-URL: Builds, https://github.com/althonos/pyaragorn/actions
Project-URL: PyPI, https://pypi.org/project/pyaragorn
Project-URL: PiWheels, https://piwheels.org/project/pyaragorn/
Requires-Python: >=3.7
Provides-Extra: test
Requires-Dist: importlib-resources; python_version < "3.9" and extra == "test"
